bd_sports_10_dataset_original/__init__.py
bd_sports_10_dataset_original/downloader.py
bd_sports_10_original-0.4.0.dist-info/licenses/LICENSE.txt
bd_sports_10_original-0.4.0.dist-info/METADATA
bd_sports_10_original-0.4.0.dist-info/WHEEL
bd_sports_10_original-0.4.0.dist-info/top_level.txt
bd_sports_10_original-0.4.0.dist-info/RECORD
