Metadata-Version: 2.4
Name: bd_sports_10_original
Version: 0.4.0
Summary: Original version of BD Sports 10 dataset with downloader and progress bar
Home-page: https://doi.org/10.57760/sciencedb.24216
Author: Wazih Ullah Tanzim <wazihullahtanzim@gmail.com>, Khondaker A. Mamun <mamun@cse.uiu.ac.bd>
License: CC BY 4.0
Classifier: Programming Language :: Python :: 3
Classifier: License :: Other/Proprietary License
Classifier: Operating System :: OS Independent
Classifier: Topic :: Utilities
Classifier: Intended Audience :: Science/Research
Requires-Python: >=3.11
License-File: LICENSE.txt
Requires-Dist: requests
Requires-Dist: tqdm
Dynamic: author
Dynamic: classifier
Dynamic: description
Dynamic: description-content-type
Dynamic: home-page
Dynamic: license
Dynamic: license-file
Dynamic: requires-dist
Dynamic: requires-python
Dynamic: summary
